{
  "puzzleId": "geo-open-001",
  "templateId": "template-15x15-open",
  "theme": "Major Rivers",
  "subTheme": "Waterways of the World",
  "difficulty": "medium",
  "words": [
    {
      "slotId": "A1",
      "answer": "NILES",
      "clue": "African river plural",
      "hint": "Blue and White in Egypt"
    },
    {
      "slotId": "A2",
      "answer": "RIO",
      "clue": "Spanish for river",
      "hint": "Grande or Bravo"
    },
    {
      "slotId": "A3",
      "answer": "DELTA",
      "clue": "River mouth formation",
      "hint": "Where rivers meet seas"
    },
    {
      "slotId": "A4",
      "answer": "RHINE",
      "clue": "German river",
      "hint": "Flows through Cologne"
    },
    {
      "slotId": "A5",
      "answer": "OAR",
      "clue": "River rowing tool",
      "hint": "Propels a boat"
    },
    {
      "slotId": "A6",
      "answer": "VOLGA",
      "clue": "Russia's longest river",
      "hint": "European Russia's lifeline"
    },
    {
      "slotId": "A7",
      "answer": "SEINE",
      "clue": "Paris river",
      "hint": "Flows past Eiffel Tower"
    },
    {
      "slotId": "A8",
      "answer": "DAM",
      "clue": "River barrier",
      "hint": "Hoover or Aswan"
    },
    {
      "slotId": "A9",
      "answer": "YANGT",
      "clue": "Yangtze start",
      "hint": "China's longest"
    },
    {
      "slotId": "A10",
      "answer": "AMAZONIAN",
      "clue": "Like the great South American river",
      "hint": "Rainforest descriptor"
    },
    {
      "slotId": "A11",
      "answer": "TIGRISE",
      "clue": "Mesopotamian river variant",
      "hint": "Iraqi waterway"
    },
    {
      "slotId": "A12",
      "answer": "EUPHRAT",
      "clue": "Euphrates start",
      "hint": "Ancient river"
    },
    {
      "slotId": "A13",
      "answer": "BED",
      "clue": "River bottom",
      "hint": "Where water flows"
    },
    {
      "slotId": "A14",
      "answer": "BANKS",
      "clue": "River sides",
      "hint": "Where you fish from"
    },
    {
      "slotId": "A15",
      "answer": "OBI",
      "clue": "Siberian river",
      "hint": "Russian Arctic river"
    },
    {
      "slotId": "A16",
      "answer": "DANUBE",
      "clue": "Blue river of Vienna",
      "hint": "Strauss waltz subject"
    },
    {
      "slotId": "A17",
      "answer": "THAMES",
      "clue": "London's river",
      "hint": "Big Ben overlooks it"
    },
    {
      "slotId": "A18",
      "answer": "MISSISSIPPIAN",
      "clue": "Like the great American river",
      "hint": "Old Man River descriptor"
    },
    {
      "slotId": "A19",
      "answer": "GANGES",
      "clue": "Sacred Hindu river",
      "hint": "Flows through Varanasi"
    },
    {
      "slotId": "A20",
      "answer": "INDUST",
      "clue": "Indus variant",
      "hint": "Pakistan's river"
    },
    {
      "slotId": "A21",
      "answer": "ERO",
      "clue": "Spanish river",
      "hint": "Iberian waterway"
    },
    {
      "slotId": "A22",
      "answer": "CONGO",
      "clue": "African river and country",
      "hint": "Second longest in Africa"
    },
    {
      "slotId": "A23",
      "answer": "ORE",
      "clue": "River deposit mineral",
      "hint": "Mined from riverbeds"
    },
    {
      "slotId": "A24",
      "answer": "ZAMBEZI",
      "clue": "Victoria Falls river",
      "hint": "African waterfall river"
    },
    {
      "slotId": "A25",
      "answer": "MEKONGS",
      "clue": "Southeast Asian rivers",
      "hint": "Vietnam's delta river"
    },
    {
      "slotId": "A26",
      "answer": "COLORADOS",
      "clue": "Western U.S. rivers",
      "hint": "Grand Canyon carver"
    },
    {
      "slotId": "A27",
      "answer": "YUKON",
      "clue": "Alaska river",
      "hint": "Gold rush territory river"
    },
    {
      "slotId": "A28",
      "answer": "POE",
      "clue": "River poet Edgar",
      "hint": "The Raven author"
    },
    {
      "slotId": "A29",
      "answer": "NIGER",
      "clue": "West African river",
      "hint": "Mali's waterway"
    },
    {
      "slotId": "A30",
      "answer": "ELBES",
      "clue": "German rivers",
      "hint": "Hamburg's river"
    },
    {
      "slotId": "A31",
      "answer": "ORO",
      "clue": "Spanish gold in rivers",
      "hint": "Prospector's find"
    },
    {
      "slotId": "A32",
      "answer": "TIBER",
      "clue": "Rome's river",
      "hint": "Vatican City border"
    },
    {
      "slotId": "A33",
      "answer": "LOIRE",
      "clue": "French valley river",
      "hint": "French wine region river"
    },
    {
      "slotId": "A34",
      "answer": "DON",
      "clue": "Russian river",
      "hint": "Quiet flows the ___"
    },
    {
      "slotId": "A35",
      "answer": "AMURS",
      "clue": "Asian border rivers",
      "hint": "Russia-China border river"
    }
  ]
}
